enhanced_google_search.py
enhanced_google_search-0.6.dist-info/METADATA
enhanced_google_search-0.6.dist-info/WHEEL
enhanced_google_search-0.6.dist-info/top_level.txt
enhanced_google_search-0.6.dist-info/RECORD
