Metadata-Version: 2.1
Name: enhanced-google-search
Version: 0.6
Summary: An enhanced google search library
Home-page: https://github.com/K-K-L-L/google_search_py
Author: KKLL
Keywords: googlesearch.py,enhanced_google_search,python google search,google search pypi,google api
Requires-Dist: httpx
